dclut/__init__.py
dclut/core.py
dclut/utils.py
dclut-0.0.3.dist-info/LICENSE.txt
dclut-0.0.3.dist-info/METADATA
dclut-0.0.3.dist-info/WHEEL
dclut-0.0.3.dist-info/top_level.txt
dclut-0.0.3.dist-info/RECORD
