Metadata-Version: 2.1
Name: dclut
Version: 0.0.3
Summary: dclut: Dimensionally Clear Look-Up Table
Home-page: https://github.com/dbheadley/dclut
Author: Drew B. Headley
Author-email: drewbheadley@gmail.com
License: MIT License
Keywords: python,binary files,lookup table,dclut
Classifier: Development Status :: 3 - Alpha
Classifier: Intended Audience :: Science/Research
Classifier: License :: OSI Approved :: MIT License
Classifier: Natural Language :: English
Classifier: Programming Language :: Python :: 3
Classifier: Operating System :: MacOS :: MacOS X
Classifier: Operating System :: Microsoft :: Windows
License-File: LICENSE.txt
Requires-Dist: numpy >=1.26.4
Requires-Dist: tqdm >=4.66.4
Requires-Dist: xarray >=2024.5.0
